gesture_classifying_model/GestureClassifier.py
gesture_classifying_model/__init__.py
gesture_classifying_model/custom_objectives.py
gesture_classifying_model/downloader.py
gesture_classifying_model-0.1.3.dist-info/DESCRIPTION.rst
gesture_classifying_model-0.1.3.dist-info/METADATA
gesture_classifying_model-0.1.3.dist-info/RECORD
gesture_classifying_model-0.1.3.dist-info/WHEEL
gesture_classifying_model-0.1.3.dist-info/metadata.json
gesture_classifying_model-0.1.3.dist-info/top_level.txt
